[
    {
        "id": "Slovak Parliamentary Election 2012",
        "turnoutTotal": 59.11,
        "turnoutIncorrect": 1.57,
        "turnoutDistributed": 57.54,
        "turnoutLeftToBeDistributed": 0.0,
        "populus": 4392451,
        "republikoveCislo": 13644,
        "populusGotIn": 2060276,
        "populusInvalidNotTurnedIn": 42717,
        "populusAttended": 2596443,
        "parties": [
            {
                "name": "SMER",
                "votes": 44.41,
                "coalitionStatus": "Alone",
                "gotIn": true,
                "mandaty": 83,
                "zostatok": 1828,
                "inGovernment": true,
                "red": 1.0,
                "green": 0.0,
                "blue": 0.0,
                "opacity": 1.0
            },
            {
                "name": "KDH",
                "votes": 8.82,
                "coalitionStatus": "Alone",
                "gotIn": true,
                "mandaty": 16,
                "zostatok": 7057,
                "inGovernment": false,
                "red": 0.25,
                "green": 0.88,
                "blue": 0.82,
                "opacity": 1.0
            },
            {
                "name": "OĽANO",
                "votes": 8.55,
                "coalitionStatus": "Small Coalition",
                "gotIn": true,
                "mandaty": 16,
                "zostatok": 233,
                "inGovernment": false,
                "red": 1.0,
                "green": 0.0,
                "blue": 1.0,
                "opacity": 1.0
            },
            {
                "name": "MOST - HÍD",
                "votes": 6.89,
                "coalitionStatus": "Alone",
                "gotIn": true,
                "mandaty": 13,
                "zostatok": 12360,
                "inGovernment": false,
                "red": 0.0,
                "green": 0.0,
                "blue": 1.0,
                "opacity": 1.0
            },
            {
                "name": "SDKÚ - DS",
                "votes": 6.09,
                "coalitionStatus": "Alone",
                "gotIn": true,
                "mandaty": 11,
                "zostatok": 5660,
                "inGovernment": false,
                "red": 0.5,
                "green": 0.0,
                "blue": 0.0,
                "opacity": 1.0
            },
            {
                "name": "SaS",
                "votes": 5.88,
                "coalitionStatus": "Alone",
                "gotIn": true,
                "mandaty": 11,
                "zostatok": 182,
                "inGovernment": false,
                "red": 0.0,
                "green": 1.0,
                "blue": 0.0,
                "opacity": 1.0
            },
            {
                "name": "SNS",
                "votes": 4.55,
                "coalitionStatus": "Alone",
                "gotIn": false,
                "mandaty": 0,
                "zostatok": 0,
                "inGovernment": false,
                "red": 0.0,
                "green": 0.0,
                "blue": 0.5,
                "opacity": 1.0
            },
            {
                "name": "SMK - MKP",
                "votes": 4.28,
                "coalitionStatus": "Alone",
                "gotIn": false,
                "mandaty": 0,
                "zostatok": 0,
                "inGovernment": false,
                "red": 0.75,
                "green": 1.0,
                "blue": 0.0,
                "opacity": 1.0
            },
            {
                "name": "99 %",
                "votes": 1.58,
                "coalitionStatus": "Alone",
                "gotIn": false,
                "mandaty": 0,
                "zostatok": 0,
                "inGovernment": false,
                "red": 1.0,
                "green": 0.86,
                "blue": 0.35,
                "opacity": 1.0
            },
            {
                "name": "ĽSNS",
                "votes": 1.58,
                "coalitionStatus": "Alone",
                "gotIn": false,
                "mandaty": 0,
                "zostatok": 0,
                "inGovernment": false,
                "red": 1.0,
                "green": 0.5,
                "blue": 0.0,
                "opacity": 1.0
            },
            {
                "name": "Zmena zdola",
                "votes": 1.29,
                "coalitionStatus": "Alone",
                "gotIn": false,
                "mandaty": 0,
                "zostatok": 0,
                "inGovernment": false,
                "red": 1.0,
                "green": 1.0,
                "blue": 0.0,
                "opacity": 1.0
            },
            {
                "name": "Strana slobodné slovo",
                "votes": 1.22,
                "coalitionStatus": "Alone",
                "gotIn": false,
                "mandaty": 0,
                "zostatok": 0,
                "inGovernment": false,
                "red": 0.5,
                "green": 0.5,
                "blue": 0.0,
                "opacity": 1.0
            },
            {
                "name": "ĽS-HZDS",
                "votes": 0.93,
                "coalitionStatus": "Alone",
                "gotIn": false,
                "mandaty": 0,
                "zostatok": 0,
                "inGovernment": false,
                "red": 0.5,
                "green": 0.9,
                "blue": 0.0,
                "opacity": 1.0
            }
        ]
    }
]
